vintasend_django/__init__.py
vintasend_django/apps.py
vintasend_django/constants.py
vintasend_django/migrations/0001_initial.py
vintasend_django/migrations/0002_notification_email_or_phone_notification_first_name_and_more.py
vintasend_django/migrations/__init__.py
vintasend_django/models.py
vintasend_django/py.typed
vintasend_django/services/__init__.py
vintasend_django/services/attachment_file.py
vintasend_django/services/notification_adapters/__init__.py
vintasend_django/services/notification_adapters/django_email.py
vintasend_django/services/notification_backends/__init__.py
vintasend_django/services/notification_backends/django_db_notification_backend.py
vintasend_django/services/notification_template_renderers/__init__.py
vintasend_django/services/notification_template_renderers/django_templated_email_renderer.py
vintasend_django/services/tests/__init__.py
vintasend_django/services/tests/test_adapters.py
vintasend_django/services/tests/test_django_db_notification_backend.py
vintasend_django/services/tests/test_template_renderers.py
vintasend_django/templates/vintasend_django/emails/base_notification.html
vintasend_django/templates/vintasend_django/emails/test/test_templated_email_body.html
vintasend_django/templates/vintasend_django/emails/test/test_templated_email_preheader.html
vintasend_django/templates/vintasend_django/emails/test/test_templated_email_subject.txt
vintasend_django/test_helpers.py
vintasend_django-1.0.1.dist-info/METADATA
vintasend_django-1.0.1.dist-info/WHEEL
vintasend_django-1.0.1.dist-info/licenses/LICENSE.txt
vintasend_django-1.0.1.dist-info/RECORD
